Workbook

Sheet Read Me
B2: Financial Performance Dashboard — Excel Project
B4: 25 companies · 5 sectors · 5 regions · Quarterly data, 2020–2024
B7: This workbook is a pure-Excel data analysis project: everything is
B8: built with native formulas, Excel Tables, data validation and
B9: conditional formatting — no macros, no external tools.
B11: Sheets in this workbook:
B13: • Data | C13: The cleaned dataset as a native Excel Table (FinancialData).
B14: • Lookup | C14: XLOOKUP / INDEX-MATCH examples to pull a single company's full record.
B15: • Pivot_Summary | C15: Cross-tab summaries by year, sector and region (formula-built; can be converted to a native PivotTable — see note on that sheet).
B16: • Dashboard | C16: Interactive dashboard — pick a Sector and Year from the dropdowns and every KPI, table and chart updates live.
B19: How to turn Pivot_Summary into a native PivotTable:
B20: 1. Click any cell inside the Data table.
B21: 2. Insert -> PivotTable -> use table 'FinancialData' as the source.
B22: 3. Drag Sector/Region/Year to Rows or Columns, and Revenue/Net_Profit to Values.

Sheet Data
A1: Company_ID | B1: Company_Name | C1: Sector | D1: Region | E1: Year | F1: Quarter | G1: Period | H1: Revenue | I1: Operating_Expenses | J1: Marketing_Spend | K1: Net_Profit | L1: Employees | M1: Customer_Count | N1: Profit_Margin_%
A2: C001 | B2: NileSoft TE | C2: Technology | D2: Jordan | E2: 2020 | F2: Q1 | G2: 2020Q1 | H2: 4582564.7 | I2: 2870941.9 | J2: 307504.57 | K2: 1404118.2 | L2: 220 | M2: 2025 | N2: 30.64
A3: C001 | B3: NileSoft TE | C3: Technology | D3: Jordan | E3: 2020 | F3: Q2 | G3: 2020Q2 | H3: 5158573.5 | I3: 2904330.1 | J3: 207536.88 | K3: 2046706.5 | L3: 220 | M3: 5339 | N3: 39.68
A4: C001 | B4: NileSoft TE | C4: Technology | D4: Jordan | E4: 2020 | F4: Q3 | G4: 2020Q3 | H4: 4930718.4 | I4: 3533545 | J4: 328384.86 | K4: 1068788.5 | L4: 220 | M4: 4442 | N4: 21.68
A5: C001 | B5: NileSoft TE | C5: Technology | D5: Jordan | E5: 2020 | F5: Q4 | G5: 2020Q4 | H5: 4159461.8 | I5: 2720344.6 | J5: 202576.87 | K5: 1236540.3 | L5: 218 | M5: 1698 | N5: 29.73
A6: C001 | B6: NileSoft TE | C6: Technology | D6: Jordan | E6: 2021 | F6: Q1 | G6: 2021Q1 | H6: 4324609.5 | I6: 3007568.7 | J6: 370184.55 | K6: 946856.23 | L6: 220 | M6: 2565 | N6: 21.89
A7: C001 | B7: NileSoft TE | C7: Technology | D7: Jordan | E7: 2021 | F7: Q2 | G7: 2021Q2 | H7: 4813693.5 | I7: 3021726.1 | J7: 238373.24 | K7: 1553594.2 | L7: 220 | M7: 3422 | N7: 32.27
A8: C001 | B8: NileSoft TE | C8: Technology | D8: Jordan | E8: 2021 | F8: Q3 | G8: 2021Q3 | H8: 4588318.8 | I8: 2675234.8 | J8: 219213.4 | K8: 1693870.6 | L8: 223 | M8: 3118 | N8: 36.92
A9: C001 | B9: NileSoft TE | C9: Technology | D9: Jordan | E9: 2021 | F9: Q4 | G9: 2021Q4 | H9: 4553783.9 | I9: 3148356.3 | J9: 359419.63 | K9: 1046008 | L9: 226 | M9: 4918 | N9: 22.97
A10: C001 | B10: NileSoft TE | C10: Technology | D10: Jordan | E10: 2022 | F10: Q1 | G10: 2022Q1 | H10: 5243376.9 | I10: 3355185.1 | J10: 424725.67 | K10: 1463466.1 | L10: 227 | M10: 2706 | N10: 27.91
A11: C001 | B11: NileSoft TE | C11: Technology | D11: Jordan | E11: 2022 | F11: Q2 | G11: 2022Q2 | H11: 5329688.4 | I11: 3610925.1 | J11: 393205.06 | K11: 1325558.2 | L11: 229 | M11: 5312 | N11: 24.87
A12: C001 | B12: NileSoft TE | C12: Technology | D12: Jordan | E12: 2022 | F12: Q3 | G12: 2022Q3 | H12: 5311545 | I12: 3193373.4 | J12: 234553.02 | K12: 1883618.5 | L12: 232 | M12: 4647 | N12: 35.46
A13: C001 | B13: NileSoft TE | C13: Technology | D13: Jordan | E13: 2022 | F13: Q4 | G13: 2022Q4 | H13: 4595537.6 | I13: 3045256.5 | J13: 268941.03 | K13: 1281340.1 | L13: 235 | M13: 2514 | N13: 27.88
... A501: C025 | B501: FactoLine IN | C501: Industrial | D501: Egypt | E501: 2024 | F501: Q4 | G501: 2024Q4 | H501: 3351505.5 | I501: 1985731.7 | J501: 101928.26 | K501: 1263845.6 | L501: 423 | M501: 2258 | N501: 37.71

Sheet Lookup
B2: Company Lookup
B4: Select Company: | C4: NileSoft TE
B6: Field | C6: Value | D6: Formula used
B7: Sector | C7: =INDEX(Data!$C$2:$C$501,MATCH($C$4,Data!$B$2:$B$501,0)) -> Technology | D7: INDEX/MATCH
B8: Region | C8: =INDEX(Data!$D$2:$D$501,MATCH($C$4,Data!$B$2:$B$501,0)) -> Jordan | D8: INDEX/MATCH
B9: Total Revenue (all quarters) | C9: =SUMIF(Data!$B$2:$B$501,$C$4,Data!$H$2:$H$501) -> 1.0194678e+08 | D9: SUMIF
B10: Total Net Profit (all quarters) | C10: =SUMIF(Data!$B$2:$B$501,$C$4,Data!$K$2:$K$501) -> 31020622 | D10: SUMIF
B11: Average Profit Margin % | C11: =AVERAGEIF(Data!$B$2:$B$501,$C$4,Data!$N$2:$N$501)/100 -> 0.303125 | D11: AVERAGEIF
B12: Average Employees per Quarter | C12: =AVERAGEIF(Data!$B$2:$B$501,$C$4,Data!$L$2:$L$501) -> 228.05 | D12: AVERAGEIF
B15: Note: INDEX/MATCH used for maximum compatibility; =XLOOKUP($C$4,...) is a direct 1-line equivalent in Excel 365/2021.

Sheet Pivot_Summary
B2: Cross-Tab Summaries (formula-built)
B3: Tip: select the Data table and use Insert > PivotTable to build a native, drag-and-drop version of these views.
B6: Revenue by Sector x Year
B7: Sector | C7: 2020 | D7: 2021 | E7: 2022 | F7: 2023 | G7: 2024 | H7: Total
B8: Finance | C8: =SUMIFS(Data!$H$2:$H$501,Data!$C$2:$C$501,$B8,Data!$E$2:$E$501,C$7) -> 1.5881183e+08 | D8: =SUMIFS(Data!$H$2:$H$501,Data!$C$2:$C$501,$B8,Data!$E$2:$E$501,D$7) -> 1.5913796e+08 | E8: =SUMIFS(Data!$H$2:$H$501,Data!$C$2:$C$501,$B8,Data!$E$2:$E$501,E$7) -> 1.6338647e+08 | F8: =SUMIFS(Data!$H$2:$H$501,Data!$C$2:$C$501,$B8,Data!$E$2:$E$501,F$7) -> 1.6475377e+08 | G8: =SUMIFS(Data!$H$2:$H$501,Data!$C$2:$C$501,$B8,Data!$E$2:$E$501,G$7) -> 1.6724552e+08 | H8: =SUM(C8:G8) -> 8.1333555e+08
B9: Healthcare | C9: =SUMIFS(Data!$H$2:$H$501,Data!$C$2:$C$501,$B9,Data!$E$2:$E$501,C$7) -> 66832211 | D9: =SUMIFS(Data!$H$2:$H$501,Data!$C$2:$C$501,$B9,Data!$E$2:$E$501,D$7) -> 69159973 | E9: =SUMIFS(Data!$H$2:$H$501,Data!$C$2:$C$501,$B9,Data!$E$2:$E$501,E$7) -> 70273273 | F9: =SUMIFS(Data!$H$2:$H$501,Data!$C$2:$C$501,$B9,Data!$E$2:$E$501,F$7) -> 72929175 | G9: =SUMIFS(Data!$H$2:$H$501,Data!$C$2:$C$501,$B9,Data!$E$2:$E$501,G$7) -> 75137650 | H9: =SUM(C9:G9) -> 3.5433228e+08
B10: Industrial | C10: =SUMIFS(Data!$H$2:$H$501,Data!$C$2:$C$501,$B10,Data!$E$2:$E$501,C$7) -> 81352970 | D10: =SUMIFS(Data!$H$2:$H$501,Data!$C$2:$C$501,$B10,Data!$E$2:$E$501,D$7) -> 1.0562139e+08 | E10: =SUMIFS(Data!$H$2:$H$501,Data!$C$2:$C$501,$B10,Data!$E$2:$E$501,E$7) -> 1.055967e+08 | F10: =SUMIFS(Data!$H$2:$H$501,Data!$C$2:$C$501,$B10,Data!$E$2:$E$501,F$7) -> 1.067981e+08 | G10: =SUMIFS(Data!$H$2:$H$501,Data!$C$2:$C$501,$B10,Data!$E$2:$E$501,G$7) -> 1.0963493e+08 | H10: =SUM(C10:G10) -> 5.0900408e+08
B11: Retail | C11: =SUMIFS(Data!$H$2:$H$501,Data!$C$2:$C$501,$B11,Data!$E$2:$E$501,C$7) -> 1.1184306e+08 | D11: =SUMIFS(Data!$H$2:$H$501,Data!$C$2:$C$501,$B11,Data!$E$2:$E$501,D$7) -> 1.4307342e+08 | E11: =SUMIFS(Data!$H$2:$H$501,Data!$C$2:$C$501,$B11,Data!$E$2:$E$501,E$7) -> 1.4888149e+08 | F11: =SUMIFS(Data!$H$2:$H$501,Data!$C$2:$C$501,$B11,Data!$E$2:$E$501,F$7) -> 1.488186e+08 | G11: =SUMIFS(Data!$H$2:$H$501,Data!$C$2:$C$501,$B11,Data!$E$2:$E$501,G$7) -> 1.4873062e+08 | H11: =SUM(C11:G11) -> 7.0134719e+08
B12: Technology | C12: =SUMIFS(Data!$H$2:$H$501,Data!$C$2:$C$501,$B12,Data!$E$2:$E$501,C$7) -> 95596506 | D12: =SUMIFS(Data!$H$2:$H$501,Data!$C$2:$C$501,$B12,Data!$E$2:$E$501,D$7) -> 99930759 | E12: =SUMIFS(Data!$H$2:$H$501,Data!$C$2:$C$501,$B12,Data!$E$2:$E$501,E$7) -> 1.0407541e+08 | F12: =SUMIFS(Data!$H$2:$H$501,Data!$C$2:$C$501,$B12,Data!$E$2:$E$501,F$7) -> 1.127308e+08 | G12: =SUMIFS(Data!$H$2:$H$501,Data!$C$2:$C$501,$B12,Data!$E$2:$E$501,G$7) -> 1.1485684e+08 | H12: =SUM(C12:G12) -> 5.2719031e+08
B15: Revenue by Sector x Region
B16: Sector | C16: Egypt | D16: Jordan | E16: Morocco | F16: Saudi Arabia | G16: UAE | H16: Total
B17: Finance | C17: =SUMIFS(Data!$H$2:$H$501,Data!$C$2:$C$501,$B17,Data!$D$2:$D$501,C$16) -> 1.7721689e+08 | D17: =SUMIFS(Data!$H$2:$H$501,Data!$C$2:$C$501,$B17,Data!$D$2:$D$501,D$16) -> 2.9865916e+08 | E17: =SUMIFS(Data!$H$2:$H$501,Data!$C$2:$C$501,$B17,Data!$D$2:$D$501,E$16) -> 1.8492928e+08 | F17: =SUMIFS(Data!$H$2:$H$501,Data!$C$2:$C$501,$B17,Data!$D$2:$D$501,F$16) -> 1.5253022e+08 | G17: =SUMIFS(Data!$H$2:$H$501,Data!$C$2:$C$501,$B17,Data!$D$2:$D$501,G$16) -> 0 | H17: =SUM(C17:G17) -> 8.1333555e+08
B18: Healthcare | C18: =SUMIFS(Data!$H$2:$H$501,Data!$C$2:$C$501,$B18,Data!$D$2:$D$501,C$16) -> 0 | D18: =SUMIFS(Data!$H$2:$H$501,Data!$C$2:$C$501,$B18,Data!$D$2:$D$501,D$16) -> 1.387795e+08 | E18: =SUMIFS(Data!$H$2:$H$501,Data!$C$2:$C$501,$B18,Data!$D$2:$D$501,E$16) -> 57504500 | F18: =SUMIFS(Data!$H$2:$H$501,Data!$C$2:$C$501,$B18,Data!$D$2:$D$501,F$16) -> 98616173 | G18: =SUMIFS(Data!$H$2:$H$501,Data!$C$2:$C$501,$B18,Data!$D$2:$D$501,G$16) -> 59432112 | H18: =SUM(C18:G18) -> 3.5433228e+08
B19: Industrial | C19: =SUMIFS(Data!$H$2:$H$501,Data!$C$2:$C$501,$B19,Data!$D$2:$D$501,C$16) -> 1.9972058e+08 | D19: =SUMIFS(Data!$H$2:$H$501,Data!$C$2:$C$501,$B19,Data!$D$2:$D$501,D$16) -> 1.1668975e+08 | E19: =SUMIFS(Data!$H$2:$H$501,Data!$C$2:$C$501,$B19,Data!$D$2:$D$501,E$16) -> 1.0263744e+08 | F19: =SUMIFS(Data!$H$2:$H$501,Data!$C$2:$C$501,$B19,Data!$D$2:$D$501,F$16) -> 89956307 | G19: =SUMIFS(Data!$H$2:$H$501,Data!$C$2:$C$501,$B19,Data!$D$2:$D$501,G$16) -> 0 | H19: =SUM(C19:G19) -> 5.0900408e+08
B20: Retail | C20: =SUMIFS(Data!$H$2:$H$501,Data!$C$2:$C$501,$B20,Data!$D$2:$D$501,C$16) -> 0 | D20: =SUMIFS(Data!$H$2:$H$501,Data!$C$2:$C$501,$B20,Data!$D$2:$D$501,D$16) -> 0 | E20: =SUMIFS(Data!$H$2:$H$501,Data!$C$2:$C$501,$B20,Data!$D$2:$D$501,E$16) -> 1.6414685e+08 | F20: =SUMIFS(Data!$H$2:$H$501,Data!$C$2:$C$501,$B20,Data!$D$2:$D$501,F$16) -> 1.4586234e+08 | G20: =SUMIFS(Data!$H$2:$H$501,Data!$C$2:$C$501,$B20,Data!$D$2:$D$501,G$16) -> 3.9133801e+08 | H20: =SUM(C20:G20) -> 7.0134719e+08
B21: Technology | C21: =SUMIFS(Data!$H$2:$H$501,Data!$C$2:$C$501,$B21,Data!$D$2:$D$501,C$16) -> 0 | D21: =SUMIFS(Data!$H$2:$H$501,Data!$C$2:$C$501,$B21,Data!$D$2:$D$501,D$16) -> 1.0194678e+08 | E21: =SUMIFS(Data!$H$2:$H$501,Data!$C$2:$C$501,$B21,Data!$D$2:$D$501,E$16) -> 3.5812645e+08 | F21: =SUMIFS(Data!$H$2:$H$501,Data!$C$2:$C$501,$B21,Data!$D$2:$D$501,F$16) -> 0 | G21: =SUMIFS(Data!$H$2:$H$501,Data!$C$2:$C$501,$B21,Data!$D$2:$D$501,G$16) -> 67117075 | H21: =SUM(C21:G21) -> 5.2719031e+08

Sheet Dashboard
B2: Financial Performance Dashboard
B4: Sector: | C4: All | E4: Year: | F4: All
B6: Total Revenue | D6: Total Net Profit | F6: Avg Profit Margin | H6: Total Employees
B7: =IF(AND($C$4="All",$F$4="All"),SUM(Data!$H$2:$H$501),IF($C$4="All",SUMIFS(Data!$H$2:$H$501,Data!$E$2:$E$501,$F$4),IF($F$4="All",SUMIFS(Data!$H$2:$H$501,Data!$C$2:$C$501,$C$4),SUMIFS(Data!$H$2:$H$501,Data!$C$2:$C$501,$C$4,Data!$E$2:$E$501,$F$4)))) -> 2.9052094e+09 | D7: =IF(AND($C$4="All",$F$4="All"),SUM(Data!$K$2:$K$501),IF($C$4="All",SUMIFS(Data!$K$2:$K$501,Data!$E$2:$E$501,$F$4),IF($F$4="All",SUMIFS(Data!$K$2:$K$501,Data!$C$2:$C$501,$C$4),SUMIFS(Data!$K$2:$K$501,Data!$C$2:$C$501,$C$4,Data!$E$2:$E$501,$F$4)))) -> 8.4390296e+08 | F7: =IF(AND($C$4="All",$F$4="All"),AVERAGE(Data!$N$2:$N$501),IF($C$4="All",AVERAGEIFS(Data!$N$2:$N$501,Data!$E$2:$E$501,$F$4),IF($F$4="All",AVERAGEIFS(Data!$N$2:$N$501,Data!$C$2:$C$501,$C$4),AVERAGEIFS(Data!$N$2:$N$501,Data!$C$2:$C$501,$C$4,Data!$E$2:$E$501,$F$4))))/100 -> 0.2922562 | H7: =IF(AND($C$4="All",$F$4="All"),SUM(Data!$L$2:$L$501),IF($C$4="All",SUMIFS(Data!$L$2:$L$501,Data!$E$2:$E$501,$F$4),IF($F$4="All",SUMIFS(Data!$L$2:$L$501,Data!$C$2:$C$501,$C$4),SUMIFS(Data!$L$2:$L$501,Data!$C$2:$C$501,$C$4,Data!$E$2:$E$501,$F$4)))) -> 128956
B10: Revenue Trend (respects filters above) | G10: Top 5 Companies by Net Profit (respects Sector filter)
B11: Year | C11: Revenue | G11: Rank | H11: Company | I11: Net Profit
B12: 2020 | C12: =IF($C$4="All",SUMIFS(Data!$H$2:$H$501,Data!$E$2:$E$501,B12),SUMIFS(Data!$H$2:$H$501,Data!$C$2:$C$501,$C$4,Data!$E$2:$E$501,B12)) -> 5.1443658e+08 | G12: 1 | H12: =INDEX($G$41:$G$65,MATCH(I12,$H$41:$H$65,0)) -> FinEdge FI | I12: =LARGE($H$41:$H$65,G12) -> 50789655
B13: 2021 | C13: =IF($C$4="All",SUMIFS(Data!$H$2:$H$501,Data!$E$2:$E$501,B13),SUMIFS(Data!$H$2:$H$501,Data!$C$2:$C$501,$C$4,Data!$E$2:$E$501,B13)) -> 5.769235e+08 | G13: 2 | H13: =INDEX($G$41:$G$65,MATCH(I13,$H$41:$H$65,0)) -> TrustBank FI | I13: =LARGE($H$41:$H$65,G13) -> 48190078
B14: 2022 | C14: =IF($C$4="All",SUMIFS(Data!$H$2:$H$501,Data!$E$2:$E$501,B14),SUMIFS(Data!$H$2:$H$501,Data!$C$2:$C$501,$C$4,Data!$E$2:$E$501,B14)) -> 5.9221333e+08 | G14: 3 | H14: =INDEX($G$41:$G$65,MATCH(I14,$H$41:$H$65,0)) -> ShopWay RE | I14: =LARGE($H$41:$H$65,G14) -> 48176833
B15: 2023 | C15: =IF($C$4="All",SUMIFS(Data!$H$2:$H$501,Data!$E$2:$E$501,B15),SUMIFS(Data!$H$2:$H$501,Data!$C$2:$C$501,$C$4,Data!$E$2:$E$501,B15)) -> 6.0603044e+08 | G15: 4 | H15: =INDEX($G$41:$G$65,MATCH(I15,$H$41:$H$65,0)) -> RetailHub RE | I15: =LARGE($H$41:$H$65,G15) -> 47745064
B16: 2024 | C16: =IF($C$4="All",SUMIFS(Data!$H$2:$H$501,Data!$E$2:$E$501,B16),SUMIFS(Data!$H$2:$H$501,Data!$C$2:$C$501,$C$4,Data!$E$2:$E$501,B16)) -> 6.1560556e+08 | G16: 5 | H16: =INDEX($G$41:$G$65,MATCH(I16,$H$41:$H$65,0)) -> NileFinance FI | I16: =LARGE($H$41:$H$65,G16) -> 47049349
G40: (helper — company totals for current sector filter)
G41: AssetPro FI | H41: =IF($C$4="All",SUMIF(Data!$B$2:$B$501,G41,Data!$K$2:$K$501),IF(INDEX(Data!$C$2:$C$501,MATCH(G41,Data!$B$2:$B$501,0))=$C$4,SUMIF(Data!$B$2:$B$501,G41,Data!$K$2:$K$501),0)) -> 39879941
G42: BazaarLine RE | H42: =IF($C$4="All",SUMIF(Data!$B$2:$B$501,G42,Data!$K$2:$K$501),IF(INDEX(Data!$C$2:$C$501,MATCH(G42,Data!$B$2:$B$501,0))=$C$4,SUMIF(Data!$B$2:$B$501,G42,Data!$K$2:$K$501),0)) -> 33898930
G43: BuildTech IN | H43: =IF($C$4="All",SUMIF(Data!$B$2:$B$501,G43,Data!$K$2:$K$501),IF(INDEX(Data!$C$2:$C$501,MATCH(G43,Data!$B$2:$B$501,0))=$C$4,SUMIF(Data!$B$2:$B$501,G43,Data!$K$2:$K$501),0)) -> 28028370
G44: CairoByte TE | H44: =IF($C$4="All",SUMIF(Data!$B$2:$B$501,G44,Data!$K$2:$K$501),IF(INDEX(Data!$C$2:$C$501,MATCH(G44,Data!$B$2:$B$501,0))=$C$4,SUMIF(Data!$B$2:$B$501,G44,Data!$K$2:$K$501),0)) -> 19989167
G45: CapitalWise FI | H45: =IF($C$4="All",SUMIF(Data!$B$2:$B$501,G45,Data!$K$2:$K$501),IF(INDEX(Data!$C$2:$C$501,MATCH(G45,Data!$B$2:$B$501,0))=$C$4,SUMIF(Data!$B$2:$B$501,G45,Data!$K$2:$K$501),0)) -> 45069144
G46: CarePlus HE | H46: =IF($C$4="All",SUMIF(Data!$B$2:$B$501,G46,Data!$K$2:$K$501),IF(INDEX(Data!$C$2:$C$501,MATCH(G46,Data!$B$2:$B$501,0))=$C$4,SUMIF(Data!$B$2:$B$501,G46,Data!$K$2:$K$501),0)) -> 23310405
G47: CodeNile TE | H47: =IF($C$4="All",SUMIF(Data!$B$2:$B$501,G47,Data!$K$2:$K$501),IF(INDEX(Data!$C$2:$C$501,MATCH(G47,Data!$B$2:$B$501,0))=$C$4,SUMIF(Data!$B$2:$B$501,G47,Data!$K$2:$K$501),0)) -> 23883783
G48: DeltaTech TE | H48: =IF($C$4="All",SUMIF(Data!$B$2:$B$501,G48,Data!$K$2:$K$501),IF(INDEX(Data!$C$2:$C$501,MATCH(G48,Data!$B$2:$B$501,0))=$C$4,SUMIF(Data!$B$2:$B$501,G48,Data!$K$2:$K$501),0)) -> 41355178
G49: FactoLine IN | H49: =IF($C$4="All",SUMIF(Data!$B$2:$B$501,G49,Data!$K$2:$K$501),IF(INDEX(Data!$C$2:$C$501,MATCH(G49,Data!$B$2:$B$501,0))=$C$4,SUMIF(Data!$B$2:$B$501,G49,Data!$K$2:$K$501),0)) -> 22219869
G50: FinEdge FI | H50: =IF($C$4="All",SUMIF(Data!$B$2:$B$501,G50,Data!$K$2:$K$501),IF(INDEX(Data!$C$2:$C$501,MATCH(G50,Data!$B$2:$B$501,0))=$C$4,SUMIF(Data!$B$2:$B$501,G50,Data!$K$2:$K$501),0)) -> 50789655
G51: HealPoint HE | H51: =IF($C$4="All",SUMIF(Data!$B$2:$B$501,G51,Data!$K$2:$K$501),IF(INDEX(Data!$C$2:$C$501,MATCH(G51,Data!$B$2:$B$501,0))=$C$4,SUMIF(Data!$B$2:$B$501,G51,Data!$K$2:$K$501),0)) -> 17305073
G52: IronWorks IN | H52: =IF($C$4="All",SUMIF(Data!$B$2:$B$501,G52,Data!$K$2:$K$501),IF(INDEX(Data!$C$2:$C$501,MATCH(G52,Data!$B$2:$B$501,0))=$C$4,SUMIF(Data!$B$2:$B$501,G52,Data!$K$2:$K$501),0)) -> 31192117
... G65: VitaLife HE | H65: =IF($C$4="All",SUMIF(Data!$B$2:$B$501,G65,Data!$K$2:$K$501),IF(INDEX(Data!$C$2:$C$501,MATCH(G65,Data!$B$2:$B$501,0))=$C$4,SUMIF(Data!$B$2:$B$501,G65,Data!$K$2:$K$501),0)) -> 17159945
